pydres/__init__.py
pydres/const.py
pydres/main.py
pydres/regexp.py
pydres-0.1.3.dist-info/LICENSE
pydres-0.1.3.dist-info/METADATA
pydres-0.1.3.dist-info/WHEEL
pydres-0.1.3.dist-info/RECORD
